{"name":"Create pet with invalid status","id":"pet-api-negative-testing;create-pet-with-invalid-status","scenarioId":"pet_negative:Create pet with invalid status","methodName":"Create pet with invalid status","testSteps":[{"number":1,"description":"Given I have invalid pet payload","duration":0,"startTime":"2026-03-30T15:59:00.943973700+05:30[Asia/Calcutta]","result":"SUCCESS","precondition":false,"level":0},{"number":2,"description":"When I send POST request to create pet","duration":1439,"startTime":"2026-03-30T15:59:00.950361700+05:30[Asia/Calcutta]","result":"SUCCESS","precondition":false,"level":0},{"number":3,"description":"Then pet negative response status should be 400 or 200","duration":0,"startTime":"2026-03-30T15:59:02.389507800+05:30[Asia/Calcutta]","result":"SUCCESS","precondition":false,"level":0}],"userStory":{"id":"pet_negative","storyName":"Pet API Negative Testing","displayName":"Pet API Negative Testing","path":"pet_negative","pathElements":[{"name":"pet_negative","description":""}],"type":"feature"},"title":"Create pet with invalid status","description":"","startTime":"2026-03-30T15:59:00.942508+05:30[Asia/Calcutta]","endTime":"2026-03-30T15:59:02.389507800+05:30[Asia/Calcutta]","duration":1,"projectKey":"","isManualTestingUpToDate":false,"manual":false,"testSource":"Cucumber","order":0,"result":"SUCCESS"}